[
    {
        "head": "Science",
        "icon": "fa fa-leaf",
        "link": "#",
        "description": "very nice it works and many more can be added later very nice it works and many more can be added latervery nice it works and many more can be added later"
    },
    {
        "head": "Maths",
        "icon": "fa fa-superscript",
        "link": "#",
        "description": "very nice it works and many more can be added later very nice it works and many more can be added latervery nice it works and many more can be added later"
    },
    {
        "head": "Creative Arts",
        "icon": "fa fa-paint-brush",
        "link": "#",
        "description": "very nice it works and many more can be added later very nice it works and many more can be added latervery nice it works and many more can be added later"
    },
    {
        "head": "Tinkering and Technology",
        "icon": "fa fa-rocket",
        "link": "#",
        "description": "tell about some thing and say about soime thing asdad"
    }
  ]